{
  "date_first_scraped": "2022-06-30",
  "description": "Las canciones que consagraron a Soda Stereo en Latinoam\u00e9rica y m\u00e1s all\u00e1.",
  "name": "Soda Stereo: 25 Esenciales",
  "tracks": [
    {
      "album": {
        "name": "Canci\u00f3n Animal (Remastered)",
        "url": "https://open.spotify.com/album/3GoSlKTNcVOp1ZxE5OOXeN"
      },
      "artists": [
        {
          "name": "Soda Stereo",
          "url": "https://open.spotify.com/artist/7An4yvF7hDYDolN4m5zKBp"
        }
      ],
      "date_added": "2020-02-27",
      "date_added_asterisk": false,
      "date_removed": null,
      "duration_ms": 263280,
      "name": "(En) El S\u00e9ptimo D\u00eda - Remasterizado 2007",
      "url": "https://open.spotify.com/track/4xVZmLJtBTedcXbDB3qYdX"
    },
    {
      "album": {
        "name": "Canci\u00f3n Animal (Remastered)",
        "url": "https://open.spotify.com/album/3GoSlKTNcVOp1ZxE5OOXeN"
      },
      "artists": [
        {
          "name": "Soda Stereo",
          "url": "https://open.spotify.com/artist/7An4yvF7hDYDolN4m5zKBp"
        }
      ],
      "date_added": "2020-02-27",
      "date_added_asterisk": false,
      "date_removed": null,
      "duration_ms": 247453,
      "name": "Canci\u00f3n Animal - Remasterizado 2007",
      "url": "https://open.spotify.com/track/6PqMi24DPibrFj9Ioc4hKL"
    },
    {
      "album": {
        "name": "Doble Vida (Remastered)",
        "url": "https://open.spotify.com/album/0mEY1U7SZdIwDWylFm2UC4"
      },
      "artists": [
        {
          "name": "Soda Stereo",
          "url": "https://open.spotify.com/artist/7An4yvF7hDYDolN4m5zKBp"
        }
      ],
      "date_added": "2020-02-27",
      "date_added_asterisk": false,
      "date_removed": null,
      "duration_ms": 312840,
      "name": "Coraz\u00f3n Delator - Remasterizado 2007",
      "url": "https://open.spotify.com/track/2zaZ81JI8KbYaL7210BB0U"
    },
    {
      "album": {
        "name": "Nada Personal (Remastered)",
        "url": "https://open.spotify.com/album/0hyq754QnaKHYpH32QnWqs"
      },
      "artists": [
        {
          "name": "Soda Stereo",
          "url": "https://open.spotify.com/artist/7An4yvF7hDYDolN4m5zKBp"
        }
      ],
      "date_added": "2020-02-27",
      "date_added_asterisk": false,
      "date_removed": null,
      "duration_ms": 229160,
      "name": "Cuando Pase El Temblor - Remasterizado 2007",
      "url": "https://open.spotify.com/track/3uMYq07Kj5m564OQwdSCrD"
    },
    {
      "album": {
        "name": "Nada Personal (Remastered)",
        "url": "https://open.spotify.com/album/0hyq754QnaKHYpH32QnWqs"
      },
      "artists": [
        {
          "name": "Soda Stereo",
          "url": "https://open.spotify.com/artist/7An4yvF7hDYDolN4m5zKBp"
        }
      ],
      "date_added": "2020-02-27",
      "date_added_asterisk": false,
      "date_removed": null,
      "duration_ms": 211666,
      "name": "Danza Rota - Remasterizado 2007",
      "url": "https://open.spotify.com/track/6WB3ovHYXvhXfXQnAeE5qj"
    },
    {
      "album": {
        "name": "Originales - 20 Exitos",
        "url": "https://open.spotify.com/album/75LbseLsPdTkMO9oUD9J8n"
      },
      "artists": [
        {
          "name": "Soda Stereo",
          "url": "https://open.spotify.com/artist/7An4yvF7hDYDolN4m5zKBp"
        }
      ],
      "date_added": "2020-02-27",
      "date_added_asterisk": false,
      "date_removed": null,
      "duration_ms": 212893,
      "name": "De M\u00fasica Ligera",
      "url": "https://open.spotify.com/track/2WD9ggmpZE7Wodh3qVVCgg"
    },
    {
      "album": {
        "name": "Signos (Remastered)",
        "url": "https://open.spotify.com/album/7s2lDvm4FwnWE5RXEoY8Gi"
      },
      "artists": [
        {
          "name": "Soda Stereo",
          "url": "https://open.spotify.com/artist/7An4yvF7hDYDolN4m5zKBp"
        }
      ],
      "date_added": "2020-02-27",
      "date_added_asterisk": false,
      "date_removed": null,
      "duration_ms": 366266,
      "name": "El Rito - Remasterizado 2007",
      "url": "https://open.spotify.com/track/61Hl37BKbYcSelJ3Sd8oU0"
    },
    {
      "album": {
        "name": "Sue\u00f1o Stereo (Remastered)",
        "url": "https://open.spotify.com/album/1A3VRbn7Kto2ov0LkSY0eg"
      },
      "artists": [
        {
          "name": "Soda Stereo",
          "url": "https://open.spotify.com/artist/7An4yvF7hDYDolN4m5zKBp"
        }
      ],
      "date_added": "2020-02-27",
      "date_added_asterisk": false,
      "date_removed": null,
      "duration_ms": 269760,
      "name": "Ella Us\u00f3 Mi Cabeza Como Un Rev\u00f3lver - Remasterizado 2007",
      "url": "https://open.spotify.com/track/5RzXSxR7BUhEtpqh77lMbR"
    },
    {
      "album": {
        "name": "Doble Vida (Remastered)",
        "url": "https://open.spotify.com/album/0mEY1U7SZdIwDWylFm2UC4"
      },
      "artists": [
        {
          "name": "Soda Stereo",
          "url": "https://open.spotify.com/artist/7An4yvF7hDYDolN4m5zKBp"
        }
      ],
      "date_added": "2020-02-27",
      "date_added_asterisk": false,
      "date_removed": null,
      "duration_ms": 346053,
      "name": "En La Ciudad De La Furia - Remasterizado 2007",
      "url": "https://open.spotify.com/track/7J2885UBOaG6x3LLkp2YGf"
    },
    {
      "album": {
        "name": "Comfort Y Musica Para Volar",
        "url": "https://open.spotify.com/album/5RJLKN7ucuVaRAUzNKtKB8"
      },
      "artists": [
        {
          "name": "Soda Stereo",
          "url": "https://open.spotify.com/artist/7An4yvF7hDYDolN4m5zKBp"
        }
      ],
      "date_added": "2020-02-27",
      "date_added_asterisk": false,
      "date_removed": null,
      "duration_ms": 294146,
      "name": "Entre Canibales - MTV Unplugged",
      "url": "https://open.spotify.com/track/060aWWmC9CrLqbhzHQifQf"
    },
    {
      "album": {
        "name": "Ruido Blanco (Remastered)",
        "url": "https://open.spotify.com/album/6cu5hIiTmKPL61p8nhpXp6"
      },
      "artists": [
        {
          "name": "Soda Stereo",
          "url": "https://open.spotify.com/artist/7An4yvF7hDYDolN4m5zKBp"
        }
      ],
      "date_added": "2020-02-27",
      "date_added_asterisk": false,
      "date_removed": null,
      "duration_ms": 338533,
      "name": "Final Caja Negra - Remasterizado 2007",
      "url": "https://open.spotify.com/track/6orWdjWmkkKQIqUdgCmx9P"
    },
    {
      "album": {
        "name": "Nada Personal (Remastered)",
        "url": "https://open.spotify.com/album/0hyq754QnaKHYpH32QnWqs"
      },
      "artists": [
        {
          "name": "Soda Stereo",
          "url": "https://open.spotify.com/artist/7An4yvF7hDYDolN4m5zKBp"
        }
      ],
      "date_added": "2020-02-27",
      "date_added_asterisk": false,
      "date_removed": null,
      "duration_ms": 198106,
      "name": "Juegos De Seducci\u00f3n - Remasterizado 2007",
      "url": "https://open.spotify.com/track/39YibHWQJLIgjQ0xWKlq6t"
    },
    {
      "album": {
        "name": "Doble Vida (Remastered)",
        "url": "https://open.spotify.com/album/0mEY1U7SZdIwDWylFm2UC4"
      },
      "artists": [
        {
          "name": "Soda Stereo",
          "url": "https://open.spotify.com/artist/7An4yvF7hDYDolN4m5zKBp"
        }
      ],
      "date_added": "2020-02-27",
      "date_added_asterisk": false,
      "date_removed": null,
      "duration_ms": 273933,
      "name": "Lo Que Sangra (La C\u00fapula) - Remasterizado 2007",
      "url": "https://open.spotify.com/track/1Ssg0m4YjM10XVTXlblIg0"
    },
    {
      "album": {
        "name": "Dynamo (Remastered)",
        "url": "https://open.spotify.com/album/4bfwXuecOmNVlPM5RStAiQ"
      },
      "artists": [
        {
          "name": "Soda Stereo",
          "url": "https://open.spotify.com/artist/7An4yvF7hDYDolN4m5zKBp"
        }
      ],
      "date_added": "2020-02-27",
      "date_added_asterisk": false,
      "date_removed": null,
      "duration_ms": 330600,
      "name": "Luna Roja - Remasterizado 2007",
      "url": "https://open.spotify.com/track/0MHENKo7srNABaALyzrYlX"
    },
    {
      "album": {
        "name": "Nada Personal (Remastered)",
        "url": "https://open.spotify.com/album/0hyq754QnaKHYpH32QnWqs"
      },
      "artists": [
        {
          "name": "Soda Stereo",
          "url": "https://open.spotify.com/artist/7An4yvF7hDYDolN4m5zKBp"
        }
      ],
      "date_added": "2020-02-27",
      "date_added_asterisk": false,
      "date_removed": null,
      "duration_ms": 292573,
      "name": "Nada Personal - Remasterizado 2007",
      "url": "https://open.spotify.com/track/4PBou1i63krEp3jKCPhxVD"
    },
    {
      "album": {
        "name": "Sue\u00f1o Stereo (Remastered)",
        "url": "https://open.spotify.com/album/1A3VRbn7Kto2ov0LkSY0eg"
      },
      "artists": [
        {
          "name": "Soda Stereo",
          "url": "https://open.spotify.com/artist/7An4yvF7hDYDolN4m5zKBp"
        }
      ],
      "date_added": "2020-02-27",
      "date_added_asterisk": false,
      "date_removed": null,
      "duration_ms": 214186,
      "name": "Paseando Por Roma - Remasterizado 2007",
      "url": "https://open.spotify.com/track/7Dk43uYcLammTOb4kS7Q9g"
    },
    {
      "album": {
        "name": "Signos (Remastered)",
        "url": "https://open.spotify.com/album/7s2lDvm4FwnWE5RXEoY8Gi"
      },
      "artists": [
        {
          "name": "Soda Stereo",
          "url": "https://open.spotify.com/artist/7An4yvF7hDYDolN4m5zKBp"
        }
      ],
      "date_added": "2020-02-27",
      "date_added_asterisk": false,
      "date_removed": null,
      "duration_ms": 292266,
      "name": "Persiana Americana - Remasterizado 2007",
      "url": "https://open.spotify.com/track/71awpJoi5bqGMBrTkHDDoL"
    },
    {
      "album": {
        "name": "Soda Stereo (Remastered)",
        "url": "https://open.spotify.com/album/3i4nU0OIi7gMmXDEhG9ZRt"
      },
      "artists": [
        {
          "name": "Soda Stereo",
          "url": "https://open.spotify.com/artist/7An4yvF7hDYDolN4m5zKBp"
        }
      ],
      "date_added": "2020-02-27",
      "date_added_asterisk": false,
      "date_removed": null,
      "duration_ms": 140346,
      "name": "Por Qu\u00e9 No Puedo Ser Del Jet Set? - Remasterizado 2007",
      "url": "https://open.spotify.com/track/2JD91cpdSGoNh9K50GmByg"
    },
    {
      "album": {
        "name": "Dynamo (Remastered)",
        "url": "https://open.spotify.com/album/4bfwXuecOmNVlPM5RStAiQ"
      },
      "artists": [
        {
          "name": "Soda Stereo",
          "url": "https://open.spotify.com/artist/7An4yvF7hDYDolN4m5zKBp"
        }
      ],
      "date_added": "2020-02-27",
      "date_added_asterisk": false,
      "date_removed": null,
      "duration_ms": 221440,
      "name": "Primavera 0 - Remasterizado 2007",
      "url": "https://open.spotify.com/track/2V4aobDkpJD7e36J8xPCL6"
    },
    {
      "album": {
        "name": "Signos (Remastered)",
        "url": "https://open.spotify.com/album/7s2lDvm4FwnWE5RXEoY8Gi"
      },
      "artists": [
        {
          "name": "Soda Stereo",
          "url": "https://open.spotify.com/artist/7An4yvF7hDYDolN4m5zKBp"
        }
      ],
      "date_added": "2020-02-27",
      "date_added_asterisk": false,
      "date_removed": null,
      "duration_ms": 317613,
      "name": "Pr\u00f3fugos - Remasterizado 2007",
      "url": "https://open.spotify.com/track/1Tja3miBbbENpqIOAqGWXa"
    },
    {
      "album": {
        "name": "Signos (Remastered)",
        "url": "https://open.spotify.com/album/7s2lDvm4FwnWE5RXEoY8Gi"
      },
      "artists": [
        {
          "name": "Soda Stereo",
          "url": "https://open.spotify.com/artist/7An4yvF7hDYDolN4m5zKBp"
        }
      ],
      "date_added": "2020-02-27",
      "date_added_asterisk": false,
      "date_removed": null,
      "duration_ms": 315346,
      "name": "Signos - Remasterizado 2007",
      "url": "https://open.spotify.com/track/09L0jTQCVyvR07arr9Gn6u"
    },
    {
      "album": {
        "name": "Soda Stereo (Remastered)",
        "url": "https://open.spotify.com/album/3i4nU0OIi7gMmXDEhG9ZRt"
      },
      "artists": [
        {
          "name": "Soda Stereo",
          "url": "https://open.spotify.com/artist/7An4yvF7hDYDolN4m5zKBp"
        }
      ],
      "date_added": "2020-02-27",
      "date_added_asterisk": false,
      "date_removed": null,
      "duration_ms": 249053,
      "name": "Sobredosis de T.V. - Remasterizado 2007",
      "url": "https://open.spotify.com/track/0aUATjSSGs7kJ7DK3J8x99"
    },
    {
      "album": {
        "name": "El Ultimo Concierto A (Remastered)",
        "url": "https://open.spotify.com/album/3QTxxZucih0hympCczXXuO"
      },
      "artists": [
        {
          "name": "Soda Stereo",
          "url": "https://open.spotify.com/artist/7An4yvF7hDYDolN4m5zKBp"
        }
      ],
      "date_added": "2020-02-27",
      "date_added_asterisk": false,
      "date_removed": null,
      "duration_ms": 244200,
      "name": "Tr\u00e1tame Suavemente - Remasterizado 2007",
      "url": "https://open.spotify.com/track/2LxyITcslKIKdMyYdHdA5l"
    },
    {
      "album": {
        "name": "Canci\u00f3n Animal (Remastered)",
        "url": "https://open.spotify.com/album/3GoSlKTNcVOp1ZxE5OOXeN"
      },
      "artists": [
        {
          "name": "Soda Stereo",
          "url": "https://open.spotify.com/artist/7An4yvF7hDYDolN4m5zKBp"
        }
      ],
      "date_added": "2020-02-27",
      "date_added_asterisk": false,
      "date_removed": null,
      "duration_ms": 145493,
      "name": "T\u00e9 Para 3 - Remasterizado 2007",
      "url": "https://open.spotify.com/track/2ZWkWB5ZC9BOuPkVuLZs8p"
    },
    {
      "album": {
        "name": "Sue\u00f1o Stereo (Remastered)",
        "url": "https://open.spotify.com/album/1A3VRbn7Kto2ov0LkSY0eg"
      },
      "artists": [
        {
          "name": "Soda Stereo",
          "url": "https://open.spotify.com/artist/7An4yvF7hDYDolN4m5zKBp"
        }
      ],
      "date_added": "2020-02-27",
      "date_added_asterisk": false,
      "date_removed": null,
      "duration_ms": 206306,
      "name": "Zoom - Remasterizado 2007",
      "url": "https://open.spotify.com/track/1djou52IdL1mVEE7gTauxo"
    }
  ],
  "url": "https://open.spotify.com/playlist/37i9dQZF1DXdJXfCVYbEo4"
}
