{
  "description": "The best new pop music by independent artists. Updates every Wednesday. Cover: Maddy Storm. Artwork: Paola Saliby\n",
  "num_followers": 156898,
  "original_name": "Fresh Finds Pop",
  "owner": {
    "name": "Spotify",
    "url": "https://open.spotify.com/user/spotify"
  },
  "snapshot_id": "MTY0OTg2MzY0NCwwMDAwMDY5NzAwMDAwMTgwMjM4OTUzYmMwMDAwMDE4MDIzODQxOWU1",
  "tracks": [
    {
      "added_at": "2022-04-13 15:27:24",
      "album": {
        "name": "Last Resort",
        "url": "https://open.spotify.com/album/4RAwawz5JYMUCMW63mgtaE"
      },
      "artists": [
        {
          "name": "Maddy Storm",
          "url": "https://open.spotify.com/artist/105IdZhgBK8zQnrtckm3NT"
        }
      ],
      "duration_ms": 129039,
      "name": "Last Resort",
      "url": "https://open.spotify.com/track/4YrFU5gRsmKv69s2L3AYdB"
    },
    {
      "added_at": "2022-04-13 15:27:24",
      "album": {
        "name": "Sex In Public",
        "url": "https://open.spotify.com/album/77V0Iyb9fUZsUNj4iCs7NV"
      },
      "artists": [
        {
          "name": "Menna",
          "url": "https://open.spotify.com/artist/5kLvMAFanr3jQ7iuciSCuM"
        }
      ],
      "duration_ms": 143531,
      "name": "Sex In Public",
      "url": "https://open.spotify.com/track/6iyWZc91qCpdJZwv3rY7xk"
    },
    {
      "added_at": "2022-04-06 15:45:49",
      "album": {
        "name": "Never Had a Chance",
        "url": "https://open.spotify.com/album/5td0jzs96pRarCswOchXN8"
      },
      "artists": [
        {
          "name": "Katherine Li",
          "url": "https://open.spotify.com/artist/6C7CCNJVIGEla8AI1LuBxI"
        }
      ],
      "duration_ms": 145520,
      "name": "Never Had a Chance",
      "url": "https://open.spotify.com/track/7kWHoZvIn3TzxUHYrszYFc"
    },
    {
      "added_at": "2022-04-13 15:27:24",
      "album": {
        "name": "Ruin Your Night",
        "url": "https://open.spotify.com/album/4zAXzBt4aTB8dcXAQsXvEA"
      },
      "artists": [
        {
          "name": "Abigail Osborn",
          "url": "https://open.spotify.com/artist/5gv5fvzy1TWJmDj7jyMiLO"
        }
      ],
      "duration_ms": 167250,
      "name": "Ruin Your Night",
      "url": "https://open.spotify.com/track/6dOmJIbASln7e4sln6sHWw"
    },
    {
      "added_at": "2022-04-13 15:27:24",
      "album": {
        "name": "i always end up leaving.",
        "url": "https://open.spotify.com/album/7x4BQ0AQcuN92NGnz6EZih"
      },
      "artists": [
        {
          "name": "will hyde",
          "url": "https://open.spotify.com/artist/3vNisYibo8wFyD4wxIbSbn"
        }
      ],
      "duration_ms": 235211,
      "name": "i always end up leaving.",
      "url": "https://open.spotify.com/track/1tgvVVE8hIryQzTVnPZUdF"
    },
    {
      "added_at": "2022-04-13 15:27:24",
      "album": {
        "name": "Ready Now",
        "url": "https://open.spotify.com/album/3HHw4HnBtG1cRc3KVbeTBn"
      },
      "artists": [
        {
          "name": "Lisa Wright",
          "url": "https://open.spotify.com/artist/48p7FJQ2yD1Ol8BWhHcfE2"
        }
      ],
      "duration_ms": 179562,
      "name": "Ready Now",
      "url": "https://open.spotify.com/track/2vjKqJ5ng4uEkN24Lbtu5f"
    },
    {
      "added_at": "2022-04-13 15:27:24",
      "album": {
        "name": "sea u n tea",
        "url": "https://open.spotify.com/album/14kyx1y0yhOWqFfsNqWLKh"
      },
      "artists": [
        {
          "name": "priestess",
          "url": "https://open.spotify.com/artist/3JDhZBUZGHTTc4Z6B1NzNj"
        }
      ],
      "duration_ms": 207274,
      "name": "sea u n tea",
      "url": "https://open.spotify.com/track/3O582rGV8pd7pWKkmSm4bc"
    },
    {
      "added_at": "2022-04-13 15:27:24",
      "album": {
        "name": "Fragile",
        "url": "https://open.spotify.com/album/4LgNaOfIQ24KSz3SENag21"
      },
      "artists": [
        {
          "name": "Bade",
          "url": "https://open.spotify.com/artist/0PtAztBAwJWdQD5BABZKtz"
        }
      ],
      "duration_ms": 181480,
      "name": "Fragile",
      "url": "https://open.spotify.com/track/08P0rCZzo3qjCk6O9p0Gjp"
    },
    {
      "added_at": "2022-04-13 15:27:24",
      "album": {
        "name": "Intuition",
        "url": "https://open.spotify.com/album/4KAh8M5voajKYfF62DN9ri"
      },
      "artists": [
        {
          "name": "Tishmal",
          "url": "https://open.spotify.com/artist/5lzYtvETBVL9Rqen5RUpPu"
        }
      ],
      "duration_ms": 186268,
      "name": "Intuition",
      "url": "https://open.spotify.com/track/5CNsudttspVuqYvMaiKhrs"
    },
    {
      "added_at": "2022-04-13 15:27:24",
      "album": {
        "name": "House of Cards",
        "url": "https://open.spotify.com/album/7Ar5VPj9yQRgSSj2wrS4B4"
      },
      "artists": [
        {
          "name": "Sophia Alexa",
          "url": "https://open.spotify.com/artist/73lvPuHcwxbYt4DzLhs7XZ"
        }
      ],
      "duration_ms": 187475,
      "name": "House of Cards",
      "url": "https://open.spotify.com/track/5lyA4FFfyi3c9bUhfFlLWe"
    },
    {
      "added_at": "2022-04-13 15:27:24",
      "album": {
        "name": "G-GIRL",
        "url": "https://open.spotify.com/album/0RVSx3zGqFF6W2nYGG8i1W"
      },
      "artists": [
        {
          "name": "Claudia Bouvette",
          "url": "https://open.spotify.com/artist/3ppelsCZFOVBUny0HZS6nn"
        }
      ],
      "duration_ms": 168960,
      "name": "G-GIRL",
      "url": "https://open.spotify.com/track/3JNEtuIPO7zYnADwzEpKwA"
    },
    {
      "added_at": "2022-04-13 15:27:24",
      "album": {
        "name": "Wishing",
        "url": "https://open.spotify.com/album/4iA2y8NwxTQvn58mpfGLux"
      },
      "artists": [
        {
          "name": "Peter Saputo",
          "url": "https://open.spotify.com/artist/2cXcO1RPtdDrkGQgJ16HdF"
        }
      ],
      "duration_ms": 192610,
      "name": "Wishing",
      "url": "https://open.spotify.com/track/7mf8dkhj7bShBIamvNIcmE"
    },
    {
      "added_at": "2022-04-13 15:27:24",
      "album": {
        "name": "Meant 4 u",
        "url": "https://open.spotify.com/album/7jfQ51q2jmIwFFSCXSBU8G"
      },
      "artists": [
        {
          "name": "Kierra the Goddess",
          "url": "https://open.spotify.com/artist/1Rm4i7p3cZu98ijRCgGDPI"
        }
      ],
      "duration_ms": 220705,
      "name": "Meant 4 u",
      "url": "https://open.spotify.com/track/6WaelsqiK0obqcmaSup3nS"
    },
    {
      "added_at": "2022-04-13 15:27:24",
      "album": {
        "name": "runaway",
        "url": "https://open.spotify.com/album/1ISAORld7KQ9gF8IlGHYvs"
      },
      "artists": [
        {
          "name": "Sejal",
          "url": "https://open.spotify.com/artist/1A7xjiZRn87g7WFbG9oMqU"
        }
      ],
      "duration_ms": 167671,
      "name": "runaway",
      "url": "https://open.spotify.com/track/1lp3Ds70JUbbN1QD5q0VsH"
    },
    {
      "added_at": "2022-03-30 04:00:00",
      "album": {
        "name": "Ordinary",
        "url": "https://open.spotify.com/album/18urkbnmlBBvY3WBHLL0kc"
      },
      "artists": [
        {
          "name": "Amber Ais",
          "url": "https://open.spotify.com/artist/3vPpiUL0ow9hQfhDMyGxle"
        }
      ],
      "duration_ms": 194000,
      "name": "Ordinary",
      "url": "https://open.spotify.com/track/2POuS8xQxLtR52E8HFtAwB"
    },
    {
      "added_at": "2022-04-13 15:27:24",
      "album": {
        "name": "Cold Hearted",
        "url": "https://open.spotify.com/album/6eMdFiAtpOGDNb868GgtGU"
      },
      "artists": [
        {
          "name": "SNJ\u00dc",
          "url": "https://open.spotify.com/artist/4FZ3Wx6Mitb6txV51DqasS"
        }
      ],
      "duration_ms": 227692,
      "name": "Cold Hearted",
      "url": "https://open.spotify.com/track/7cB40VKCyeR4IZ90r0sVhN"
    },
    {
      "added_at": "2022-04-13 15:27:24",
      "album": {
        "name": "What Then",
        "url": "https://open.spotify.com/album/5xd8cRFKCQSeuJkPKtpjCv"
      },
      "artists": [
        {
          "name": "McCall",
          "url": "https://open.spotify.com/artist/229NvsczXKwdH0DkPg4uwT"
        }
      ],
      "duration_ms": 157906,
      "name": "What Then",
      "url": "https://open.spotify.com/track/7LzRh6rSeOwIfluOllUvxk"
    },
    {
      "added_at": "2022-04-13 15:27:24",
      "album": {
        "name": "everything is fine",
        "url": "https://open.spotify.com/album/7g21xIlcdpY8DiZ65iTcad"
      },
      "artists": [
        {
          "name": "shallow pools",
          "url": "https://open.spotify.com/artist/5wg5i56CcvaCrZrveXt228"
        }
      ],
      "duration_ms": 188792,
      "name": "everything is fine",
      "url": "https://open.spotify.com/track/3KUoaFS4cNVRKAqYFCpDQg"
    },
    {
      "added_at": "2022-04-13 15:27:24",
      "album": {
        "name": "Same Spoon",
        "url": "https://open.spotify.com/album/1oxzfVto0zDBiZ27QndqL1"
      },
      "artists": [
        {
          "name": "Takkin",
          "url": "https://open.spotify.com/artist/6YJXZoTvzi4NK03J19R73d"
        }
      ],
      "duration_ms": 197826,
      "name": "Same Spoon",
      "url": "https://open.spotify.com/track/21E8AG9rDGRtziaFWGf9aU"
    },
    {
      "added_at": "2022-04-06 15:45:49",
      "album": {
        "name": "The Way You Are",
        "url": "https://open.spotify.com/album/3mybFM7ibDln2Efcj1r3T1"
      },
      "artists": [
        {
          "name": "Lois",
          "url": "https://open.spotify.com/artist/6qAYnkQmOOQCBPPmyd4lo1"
        }
      ],
      "duration_ms": 175950,
      "name": "The Way You Are",
      "url": "https://open.spotify.com/track/52GPw706N71AnEaa1oPBtU"
    },
    {
      "added_at": "2022-04-13 15:27:24",
      "album": {
        "name": "TOGAF (Tired Of Giving A Fuck)",
        "url": "https://open.spotify.com/album/2inGUUMkCRM4J1Rc8yuHyK"
      },
      "artists": [
        {
          "name": "Nicholas Mick",
          "url": "https://open.spotify.com/artist/0HmWuWhwxKEIuwTVtFyI8s"
        }
      ],
      "duration_ms": 122855,
      "name": "TOGAF (Tired Of Giving A Fuck)",
      "url": "https://open.spotify.com/track/5IpEA4IJ82dBpyayJiU5va"
    },
    {
      "added_at": "2022-04-13 15:27:24",
      "album": {
        "name": "Birthday",
        "url": "https://open.spotify.com/album/2L11I1HBuWIlrTBBRjXuFi"
      },
      "artists": [
        {
          "name": "Feliciana",
          "url": "https://open.spotify.com/artist/49qJvbUyRJ7r4ae4QYhTFY"
        }
      ],
      "duration_ms": 133012,
      "name": "Birthday",
      "url": "https://open.spotify.com/track/32lSBUAwseG81GL0VjeXEz"
    },
    {
      "added_at": "2022-04-13 15:27:24",
      "album": {
        "name": "Falling Into You",
        "url": "https://open.spotify.com/album/2OfF1GFffwahzKWrwwgsXq"
      },
      "artists": [
        {
          "name": "Blake Proehl",
          "url": "https://open.spotify.com/artist/1RgYPu8VR3b5sXupFPGMAO"
        }
      ],
      "duration_ms": 206573,
      "name": "Falling Into You",
      "url": "https://open.spotify.com/track/0z6AuCoTK782Gb4d0JhALP"
    },
    {
      "added_at": "2022-04-13 15:27:24",
      "album": {
        "name": "Cartier",
        "url": "https://open.spotify.com/album/5KKa4O8V0YmpcKdqDfBNZz"
      },
      "artists": [
        {
          "name": "Caroline Dare",
          "url": "https://open.spotify.com/artist/729VtCqRPf0MwVTXAPz7wr"
        }
      ],
      "duration_ms": 200563,
      "name": "Cartier",
      "url": "https://open.spotify.com/track/5Dg385wbg8UpFsPGF7mKSN"
    },
    {
      "added_at": "2022-04-13 15:27:24",
      "album": {
        "name": "3 Dots",
        "url": "https://open.spotify.com/album/2zLXDihNr5mOCBPs48xVlx"
      },
      "artists": [
        {
          "name": "Wheelwright",
          "url": "https://open.spotify.com/artist/2uliQptJvJh6ZjWB98LBRU"
        }
      ],
      "duration_ms": 223303,
      "name": "3 Dots",
      "url": "https://open.spotify.com/track/70Av51U07ACdrKZUJJBPGM"
    },
    {
      "added_at": "2022-04-13 15:27:24",
      "album": {
        "name": "Disney Bitch",
        "url": "https://open.spotify.com/album/47vIhafcuqfH9TNgTuBTju"
      },
      "artists": [
        {
          "name": "Killer Kennedy",
          "url": "https://open.spotify.com/artist/4Qgwf1NflcpEcVHCuCw9Gd"
        }
      ],
      "duration_ms": 114461,
      "name": "Disney Bitch",
      "url": "https://open.spotify.com/track/2jRuSsnB481aumCPQ9fJRZ"
    },
    {
      "added_at": "2022-04-13 15:27:24",
      "album": {
        "name": "Bloom Indigo",
        "url": "https://open.spotify.com/album/5bNmet8sQZdUM0c89xHq9U"
      },
      "artists": [
        {
          "name": "Hollis",
          "url": "https://open.spotify.com/artist/28KOnhhvUnyvgRNXEQ41WL"
        },
        {
          "name": "Dresage",
          "url": "https://open.spotify.com/artist/5dFeAUPKdp9Id4E1RYqez2"
        }
      ],
      "duration_ms": 166373,
      "name": "Bloom Indigo",
      "url": "https://open.spotify.com/track/2ldyLfiut0Q3bayS5MNNZD"
    },
    {
      "added_at": "2022-04-06 15:45:49",
      "album": {
        "name": "Best Dressed Ex / Your New Tattoo",
        "url": "https://open.spotify.com/album/7weBwRSKvIl9cMq5Xbtfmz"
      },
      "artists": [
        {
          "name": "Freddie Lewis",
          "url": "https://open.spotify.com/artist/2Y08LH0PaXKiJNNuQQ827y"
        }
      ],
      "duration_ms": 213355,
      "name": "Best Dressed Ex",
      "url": "https://open.spotify.com/track/5N6zMhMWFeJmDSgoDGuCC5"
    },
    {
      "added_at": "2022-04-06 15:45:49",
      "album": {
        "name": "Honestly I'm Disappointed",
        "url": "https://open.spotify.com/album/4ueJumymqxktXKi8uSfzF1"
      },
      "artists": [
        {
          "name": "Kate Grahn",
          "url": "https://open.spotify.com/artist/3uKUYOnOlOpYj7quHnLtFv"
        }
      ],
      "duration_ms": 139679,
      "name": "Honestly I'm Disappointed",
      "url": "https://open.spotify.com/track/4XeELrZsC6BNUF9RjGdDx3"
    },
    {
      "added_at": "2022-04-06 15:45:49",
      "album": {
        "name": "Permanent Damage",
        "url": "https://open.spotify.com/album/0GH5fNklrAR8q4U0BJKnOO"
      },
      "artists": [
        {
          "name": "Kylie Muse",
          "url": "https://open.spotify.com/artist/5KUrN1Ip3QoemX2Dq4kGS5"
        }
      ],
      "duration_ms": 166400,
      "name": "Permanent Damage",
      "url": "https://open.spotify.com/track/2vzOjLxnzBwo8M2hNS8AOX"
    },
    {
      "added_at": "2022-03-30 04:00:00",
      "album": {
        "name": "Get Wild",
        "url": "https://open.spotify.com/album/6ctKa1fF9AWTGoU2Gf4PII"
      },
      "artists": [
        {
          "name": "LOVE SICK",
          "url": "https://open.spotify.com/artist/3oX23qsyfFiuzyXDBbmhXO"
        }
      ],
      "duration_ms": 201399,
      "name": "Get Wild",
      "url": "https://open.spotify.com/track/05vIJo5TbBbbYo7G5bB1Zy"
    },
    {
      "added_at": "2022-04-06 15:45:49",
      "album": {
        "name": "tied up",
        "url": "https://open.spotify.com/album/77ZuKbhvKaHggoL6BK1rZR"
      },
      "artists": [
        {
          "name": "starfall",
          "url": "https://open.spotify.com/artist/6h0Wppb5dQnlGpY2zuGstd"
        }
      ],
      "duration_ms": 155200,
      "name": "tied up",
      "url": "https://open.spotify.com/track/5r6SvlgLsOICbY8p1J7ARK"
    },
    {
      "added_at": "2022-04-06 15:45:49",
      "album": {
        "name": "sorry it didn't work out",
        "url": "https://open.spotify.com/album/5BP6SX5xnt4qvitpCBVKJw"
      },
      "artists": [
        {
          "name": "Papa",
          "url": "https://open.spotify.com/artist/3yhUYybUxwJn1or7zHXWHy"
        }
      ],
      "duration_ms": 149690,
      "name": "sorry it didn't work out",
      "url": "https://open.spotify.com/track/4fhWjpuQMX2JelLPLhTm0a"
    },
    {
      "added_at": "2022-04-06 15:45:49",
      "album": {
        "name": "Timeless",
        "url": "https://open.spotify.com/album/37wuXOHCDBPMdoZbzhxGq4"
      },
      "artists": [
        {
          "name": "HOLLISS",
          "url": "https://open.spotify.com/artist/0DqLsOH3Ou5KUMsbosBaHQ"
        }
      ],
      "duration_ms": 183529,
      "name": "Timeless",
      "url": "https://open.spotify.com/track/621ZeUkBOs93NwbWixnMHD"
    },
    {
      "added_at": "2022-04-06 15:45:49",
      "album": {
        "name": "For the Rest of Our Whole Lives",
        "url": "https://open.spotify.com/album/4s9IKn0ld5utVoJVl6NJJR"
      },
      "artists": [
        {
          "name": "Dillon Davis",
          "url": "https://open.spotify.com/artist/3Uhwg0juoL0tQIR9Xgwy7j"
        }
      ],
      "duration_ms": 205056,
      "name": "For the Rest of Our Whole Lives",
      "url": "https://open.spotify.com/track/3OwZL2iLBt9JOcGWMuyCDj"
    },
    {
      "added_at": "2022-04-06 15:45:49",
      "album": {
        "name": "If It's Not Forever",
        "url": "https://open.spotify.com/album/5OhIJcMEADcrAKH5kkAvzT"
      },
      "artists": [
        {
          "name": "Cassidy Mann",
          "url": "https://open.spotify.com/artist/6RJL8I7zuC8mVHP5u9juRu"
        }
      ],
      "duration_ms": 189548,
      "name": "Tropical Sour Candy",
      "url": "https://open.spotify.com/track/0zwKGD9KXvdIfZXlCb0WzI"
    },
    {
      "added_at": "2022-03-30 04:00:00",
      "album": {
        "name": "Pretend",
        "url": "https://open.spotify.com/album/6t1xNIVOiLRS8Kz45mp4xm"
      },
      "artists": [
        {
          "name": "Sebastian Javier",
          "url": "https://open.spotify.com/artist/7jEax0MCKxovBHDU6AaFca"
        }
      ],
      "duration_ms": 161952,
      "name": "Pretend",
      "url": "https://open.spotify.com/track/5ZdXp6ruQlKZhd0udym6Ud"
    },
    {
      "added_at": "2022-04-06 15:45:49",
      "album": {
        "name": "Apartment in LA",
        "url": "https://open.spotify.com/album/18qldIwClrVp0uG5LhBtKO"
      },
      "artists": [
        {
          "name": "Caroline Taylor",
          "url": "https://open.spotify.com/artist/0zKM9VGhndnA3gsYAZPFtB"
        }
      ],
      "duration_ms": 192515,
      "name": "Apartment in LA",
      "url": "https://open.spotify.com/track/6LRVfEY6cSlGo4Pv5e9JFp"
    },
    {
      "added_at": "2022-04-06 15:45:49",
      "album": {
        "name": "Check Check",
        "url": "https://open.spotify.com/album/2cjrye5FaoK9ExMD1rwWa6"
      },
      "artists": [
        {
          "name": "OhEm",
          "url": "https://open.spotify.com/artist/5a9tuA9hAvmwXEjk9t6x0U"
        }
      ],
      "duration_ms": 243874,
      "name": "Check Check",
      "url": "https://open.spotify.com/track/15ibpzLxaUqycubbAfPFpe"
    },
    {
      "added_at": "2022-04-06 15:45:49",
      "album": {
        "name": "Sober",
        "url": "https://open.spotify.com/album/7vhUiJ7vD2IXIcwEcGCu37"
      },
      "artists": [
        {
          "name": "RYMAN",
          "url": "https://open.spotify.com/artist/1ZUNE7b5nNiN31AnJ0Smqj"
        }
      ],
      "duration_ms": 198870,
      "name": "Sober",
      "url": "https://open.spotify.com/track/0fkLqdFQagwuoXC7ne2tkg"
    },
    {
      "added_at": "2022-04-06 15:45:49",
      "album": {
        "name": "Silent Movie",
        "url": "https://open.spotify.com/album/1ZeT3LQu8fgK6Qc3BZX3CY"
      },
      "artists": [
        {
          "name": "Erica Manzoli",
          "url": "https://open.spotify.com/artist/23fOuvbhI889XOAcLhvaBJ"
        }
      ],
      "duration_ms": 136213,
      "name": "Silent Movie",
      "url": "https://open.spotify.com/track/6W85fbQbVmKkEQs1W88vQK"
    },
    {
      "added_at": "2022-04-06 15:45:49",
      "album": {
        "name": "SHIT SHOW",
        "url": "https://open.spotify.com/album/3wqeXZkmQcbxkcUbyAZ2Ce"
      },
      "artists": [
        {
          "name": "penelope Q",
          "url": "https://open.spotify.com/artist/70ovkdfy4QSPHKJQ0Qy9zR"
        }
      ],
      "duration_ms": 168000,
      "name": "SHIT SHOW",
      "url": "https://open.spotify.com/track/2Tuxu2ajjANzS61aDFe5o5"
    },
    {
      "added_at": "2022-04-06 15:45:49",
      "album": {
        "name": "Eila",
        "url": "https://open.spotify.com/album/5qF2uUmuZsP8YXzza4i0d9"
      },
      "artists": [
        {
          "name": "Eila",
          "url": "https://open.spotify.com/artist/3QgHVqOGDEvvWFr5fI2DTW"
        },
        {
          "name": "Alianna",
          "url": "https://open.spotify.com/artist/4BunrsDi4qKwGwtucAVx9T"
        }
      ],
      "duration_ms": 186960,
      "name": "New Life",
      "url": "https://open.spotify.com/track/4JOKkUKCY95GjTuhYtHfSg"
    },
    {
      "added_at": "2022-04-06 15:45:49",
      "album": {
        "name": "Elevated",
        "url": "https://open.spotify.com/album/64FWfFtiurDdKQ17dMNPqj"
      },
      "artists": [
        {
          "name": "Night Swimmer",
          "url": "https://open.spotify.com/artist/18VQpw9DeYcTQpei170WuB"
        }
      ],
      "duration_ms": 216923,
      "name": "Elevated",
      "url": "https://open.spotify.com/track/3A22lR8VSNAJ6UPqDLZ8eK"
    },
    {
      "added_at": "2022-03-23 13:28:07",
      "album": {
        "name": "THE SNAKE",
        "url": "https://open.spotify.com/album/6MUnBgFIOhLgnf7h5pmZGm"
      },
      "artists": [
        {
          "name": "Lana Lubany",
          "url": "https://open.spotify.com/artist/53jnd1fhXV7lbXSfjgk1WR"
        }
      ],
      "duration_ms": 176953,
      "name": "THE SNAKE",
      "url": "https://open.spotify.com/track/4tRXJwAv2zZrcDcfjTUekQ"
    },
    {
      "added_at": "2022-04-06 15:45:49",
      "album": {
        "name": "THOUGHTS & FEARS",
        "url": "https://open.spotify.com/album/6OyNnZygqqxENKNYGXFd0W"
      },
      "artists": [
        {
          "name": "Mindy",
          "url": "https://open.spotify.com/artist/4IVRW82OzrZZ4qZSf0xYJF"
        }
      ],
      "duration_ms": 272038,
      "name": "THOUGHTS & FEARS",
      "url": "https://open.spotify.com/track/3v4sp31nbjhQ2rwlbgqwOI"
    },
    {
      "added_at": "2022-04-06 15:45:49",
      "album": {
        "name": "Dead",
        "url": "https://open.spotify.com/album/4c2aw2xQDzSHqesCIfeCMm"
      },
      "artists": [
        {
          "name": "Baby Jane",
          "url": "https://open.spotify.com/artist/3scHMUcB85BflinC8FclbI"
        }
      ],
      "duration_ms": 157565,
      "name": "Dead",
      "url": "https://open.spotify.com/track/3z4bbV92bY6K2A5EMXpLhI"
    },
    {
      "added_at": "2022-04-06 15:45:49",
      "album": {
        "name": "Inmyhead",
        "url": "https://open.spotify.com/album/4W1j4Q6S25vpJwtTc2T5Wo"
      },
      "artists": [
        {
          "name": "Shadowthekiddd",
          "url": "https://open.spotify.com/artist/4yUeXyp8L8mZilO11Q3567"
        }
      ],
      "duration_ms": 143852,
      "name": "Inmyhead",
      "url": "https://open.spotify.com/track/5ntJCvGZvpQkErJokU4o1u"
    },
    {
      "added_at": "2022-04-06 15:45:49",
      "album": {
        "name": "Fabricated",
        "url": "https://open.spotify.com/album/2wDZQ2KZF8k6tPM2Ai6Pw0"
      },
      "artists": [
        {
          "name": "Katy for Kings",
          "url": "https://open.spotify.com/artist/2AofFktDEQuzk1LKKEQ9Ox"
        }
      ],
      "duration_ms": 169588,
      "name": "Fabricated",
      "url": "https://open.spotify.com/track/0Zq7eJrwaAZyyBf1yOyFop"
    },
    {
      "added_at": "2022-04-06 15:45:49",
      "album": {
        "name": "Liars",
        "url": "https://open.spotify.com/album/2RRSldjXULZzO7eK5qwk2T"
      },
      "artists": [
        {
          "name": "st.James",
          "url": "https://open.spotify.com/artist/0WqfvIHk0iWcqlp4UsZyMC"
        }
      ],
      "duration_ms": 151287,
      "name": "Liars",
      "url": "https://open.spotify.com/track/1aeMR6HZyexprB1AePlVEs"
    },
    {
      "added_at": "2022-03-30 04:00:00",
      "album": {
        "name": "TIM BURTON",
        "url": "https://open.spotify.com/album/6oABSgthAWalcNbsL8VWKF"
      },
      "artists": [
        {
          "name": "RAEGAN",
          "url": "https://open.spotify.com/artist/2nB2BHirpyBx2sJc4QKfwz"
        }
      ],
      "duration_ms": 152571,
      "name": "TIM BURTON",
      "url": "https://open.spotify.com/track/5HnhgU9FS7RNnFgkBy48wS"
    },
    {
      "added_at": "2022-03-30 04:00:00",
      "album": {
        "name": "Him or Her",
        "url": "https://open.spotify.com/album/1Jdgh6TIoCoRvVewahwybF"
      },
      "artists": [
        {
          "name": "Sei Selina",
          "url": "https://open.spotify.com/artist/02h0nhiB21xYexvsxge3z9"
        }
      ],
      "duration_ms": 231546,
      "name": "The Way",
      "url": "https://open.spotify.com/track/73FZI0ss9uyhLbZwwNqDms"
    },
    {
      "added_at": "2022-03-30 04:00:00",
      "album": {
        "name": "Stone Love",
        "url": "https://open.spotify.com/album/4YG7zLw6PgSNnlqeqZeb5Z"
      },
      "artists": [
        {
          "name": "Hannah Felisa",
          "url": "https://open.spotify.com/artist/3RMtvXcT4eH5swWPJim9cp"
        }
      ],
      "duration_ms": 197948,
      "name": "Stone Love",
      "url": "https://open.spotify.com/track/3dupodqlwjIIfekJ5nOdOW"
    },
    {
      "added_at": "2022-03-30 04:00:00",
      "album": {
        "name": "GONE",
        "url": "https://open.spotify.com/album/1BmTqO87yk4ML8LadOM30G"
      },
      "artists": [
        {
          "name": "Jake Neumar",
          "url": "https://open.spotify.com/artist/69weKTfYYEBofMntV36KPG"
        }
      ],
      "duration_ms": 160329,
      "name": "GONE",
      "url": "https://open.spotify.com/track/3hA0CWYwHmwnYKaETShBNn"
    },
    {
      "added_at": "2022-03-30 04:00:00",
      "album": {
        "name": "So Emotional",
        "url": "https://open.spotify.com/album/2DcoRy7NY9K9WQ6QXS6AI8"
      },
      "artists": [
        {
          "name": "Beren Olivia",
          "url": "https://open.spotify.com/artist/5WGPbnx9LqsQYXgpnUI3DZ"
        }
      ],
      "duration_ms": 174266,
      "name": "So Emotional",
      "url": "https://open.spotify.com/track/0TMa5i5gaTQDOTaYMOCvtM"
    },
    {
      "added_at": "2022-03-30 04:00:00",
      "album": {
        "name": "Tell Me",
        "url": "https://open.spotify.com/album/5G0S0RDVw7yKKzW3krfKlV"
      },
      "artists": [
        {
          "name": "WILSN",
          "url": "https://open.spotify.com/artist/2ymjQZjPQe0pziQ67Y8Ncr"
        }
      ],
      "duration_ms": 222496,
      "name": "Tell Me",
      "url": "https://open.spotify.com/track/2UvjzFa5j6V2oi6PStN2TT"
    },
    {
      "added_at": "2022-03-30 04:00:00",
      "album": {
        "name": "Suburbia",
        "url": "https://open.spotify.com/album/7JSpsa4Nzkx4d55wp9BWoh"
      },
      "artists": [
        {
          "name": "Carly Rose",
          "url": "https://open.spotify.com/artist/0Z49rYPKsyCCLGq1UiHrBe"
        }
      ],
      "duration_ms": 197828,
      "name": "Suburbia",
      "url": "https://open.spotify.com/track/4ScG2daMakzbeEUbnaIJp7"
    },
    {
      "added_at": "2022-03-30 04:00:00",
      "album": {
        "name": "Assignment / Stupid.",
        "url": "https://open.spotify.com/album/003ukg8dLyQEl1xkD6hKxY"
      },
      "artists": [
        {
          "name": "Ni/Co",
          "url": "https://open.spotify.com/artist/2IR0GSCHsTo7gSw8HHLBnr"
        },
        {
          "name": "Jonathan & Friends",
          "url": "https://open.spotify.com/artist/7iGyHL0MMwmyScIHOuW7Lo"
        }
      ],
      "duration_ms": 156521,
      "name": "Stupid.",
      "url": "https://open.spotify.com/track/0VPviA6kqKtsmpBKgZBKM8"
    },
    {
      "added_at": "2022-03-30 04:00:00",
      "album": {
        "name": "Devil In A Dress",
        "url": "https://open.spotify.com/album/6ViBFxxd5c6e1WUCDbRMAk"
      },
      "artists": [
        {
          "name": "Rhea Raj",
          "url": "https://open.spotify.com/artist/7inC0Ybb6OGEMB7GP8nfi1"
        }
      ],
      "duration_ms": 111467,
      "name": "Devil In A Dress",
      "url": "https://open.spotify.com/track/0IidWnhWbmVcVa5vzXucav"
    },
    {
      "added_at": "2022-03-30 04:00:00",
      "album": {
        "name": "AT LEAST I'M GOOD AT IT",
        "url": "https://open.spotify.com/album/3ALTi5aB725LhPjGikjG4Z"
      },
      "artists": [
        {
          "name": "NERIAH",
          "url": "https://open.spotify.com/artist/1dUrqVHcv2FCXxlIqzIbiG"
        }
      ],
      "duration_ms": 148398,
      "name": "AT LEAST I'M GOOD AT IT",
      "url": "https://open.spotify.com/track/1KrLtIuOgZ1QiIxBqGb4NF"
    },
    {
      "added_at": "2022-03-30 04:00:00",
      "album": {
        "name": "Superpowers: part I",
        "url": "https://open.spotify.com/album/6H0lYr8rp08c2idHjqL6KU"
      },
      "artists": [
        {
          "name": "BYRNE",
          "url": "https://open.spotify.com/artist/06a0KPufkYNdb0mZ9CcSho"
        }
      ],
      "duration_ms": 137665,
      "name": "Where The Wild Things Are",
      "url": "https://open.spotify.com/track/0TqCoJvdIs4CtDaQpv7JfH"
    },
    {
      "added_at": "2022-03-23 13:28:07",
      "album": {
        "name": "Love Warning",
        "url": "https://open.spotify.com/album/7lxYLbpNrfnTxocu2VN9ql"
      },
      "artists": [
        {
          "name": "Cat Janice",
          "url": "https://open.spotify.com/artist/7kNpF2nj7eVgcVo8k6pWkz"
        }
      ],
      "duration_ms": 219250,
      "name": "Love Warning",
      "url": "https://open.spotify.com/track/75jC2iGlGyS0f2dEkd5FE9"
    },
    {
      "added_at": "2022-03-30 04:00:00",
      "album": {
        "name": "Call My Own",
        "url": "https://open.spotify.com/album/6fKaC3BsUu5DeKzcvrg7ko"
      },
      "artists": [
        {
          "name": "Isabel Pless",
          "url": "https://open.spotify.com/artist/4lOW9vOCRgeh8peyg1mw1b"
        }
      ],
      "duration_ms": 175636,
      "name": "Call My Own",
      "url": "https://open.spotify.com/track/2Tp03ZfNBqXL8Ny0g9e8sM"
    },
    {
      "added_at": "2022-03-16 04:00:00",
      "album": {
        "name": "Love On TV",
        "url": "https://open.spotify.com/album/1LXU3kEAWsG3j41EjdFOT7"
      },
      "artists": [
        {
          "name": "KAIRO",
          "url": "https://open.spotify.com/artist/74fcIBekHLf4hucCT3My0v"
        }
      ],
      "duration_ms": 193560,
      "name": "Love On TV",
      "url": "https://open.spotify.com/track/70pzDL6WXCbT4RhW29TGgY"
    },
    {
      "added_at": "2022-03-30 04:00:00",
      "album": {
        "name": "Baby Boy",
        "url": "https://open.spotify.com/album/04oxYONJ0s4hcjkZKrkJF2"
      },
      "artists": [
        {
          "name": "Holdan",
          "url": "https://open.spotify.com/artist/4VRRVLm2L1yeCKSFGR57zl"
        }
      ],
      "duration_ms": 256377,
      "name": "Baby Boy",
      "url": "https://open.spotify.com/track/3Z4TXeUrtnXcpUVwHfjBPw"
    },
    {
      "added_at": "2022-03-30 04:00:00",
      "album": {
        "name": "Lovely Weather",
        "url": "https://open.spotify.com/album/4H486vjhzhdNFu7cRWw7Ay"
      },
      "artists": [
        {
          "name": "Lowheart",
          "url": "https://open.spotify.com/artist/6z9ujG6FHp0LnqmcXk586c"
        }
      ],
      "duration_ms": 187760,
      "name": "Lovely Weather",
      "url": "https://open.spotify.com/track/0bSsno2oGtfZZHSnuLZsGl"
    },
    {
      "added_at": "2022-03-30 04:00:00",
      "album": {
        "name": "Don't Take Me Home",
        "url": "https://open.spotify.com/album/65oWIAPrQd39K0yn3CGZ8X"
      },
      "artists": [
        {
          "name": "Wendy Lucas",
          "url": "https://open.spotify.com/artist/0QS3e81yxqcAh6izLUEa3a"
        }
      ],
      "duration_ms": 209268,
      "name": "Don't Take Me Home",
      "url": "https://open.spotify.com/track/1EzBl3B4BwfNfrfM4ijheK"
    },
    {
      "added_at": "2022-03-30 04:00:00",
      "album": {
        "name": "Liar",
        "url": "https://open.spotify.com/album/2NXTdIWQLR45B1jJFgTKZj"
      },
      "artists": [
        {
          "name": "Jake Daniels",
          "url": "https://open.spotify.com/artist/3AYZMgvmzNKc3cGmJUSITh"
        }
      ],
      "duration_ms": 158400,
      "name": "Liar",
      "url": "https://open.spotify.com/track/3GN4qe6CrarjGTZU2DdpEe"
    },
    {
      "added_at": "2022-03-30 04:00:00",
      "album": {
        "name": "Slitted Tongue",
        "url": "https://open.spotify.com/album/5co49ntVCysUnAHuIBiBh2"
      },
      "artists": [
        {
          "name": "L\u00e9onie Gray",
          "url": "https://open.spotify.com/artist/1kt4PKJ7KueinsGBtDdf7b"
        }
      ],
      "duration_ms": 188713,
      "name": "Slitted Tongue",
      "url": "https://open.spotify.com/track/6lZpYp8Cd6tQlCDchtg3ch"
    },
    {
      "added_at": "2022-03-30 04:00:00",
      "album": {
        "name": "Driving Home",
        "url": "https://open.spotify.com/album/5JVpAaWPJiOteo0YH4ymsi"
      },
      "artists": [
        {
          "name": "Breakfast Road",
          "url": "https://open.spotify.com/artist/444KERNPfWuFIVw7TxEev6"
        }
      ],
      "duration_ms": 141907,
      "name": "Driving Home",
      "url": "https://open.spotify.com/track/459i1iK7QehIvYQTMHXvIQ"
    },
    {
      "added_at": "2022-03-23 13:28:07",
      "album": {
        "name": "Burn Again",
        "url": "https://open.spotify.com/album/002riN5oRTYuhXmc89gvgp"
      },
      "artists": [
        {
          "name": "Markella",
          "url": "https://open.spotify.com/artist/2RMXPfuWbGwHulRBAHGqbt"
        }
      ],
      "duration_ms": 205853,
      "name": "Burn Again",
      "url": "https://open.spotify.com/track/1n0R7zfIgTGKeJOnr6P4uQ"
    },
    {
      "added_at": "2022-03-23 13:28:07",
      "album": {
        "name": "Boy Meets World",
        "url": "https://open.spotify.com/album/0DTtY519Qm7yGBqiBdhUs6"
      },
      "artists": [
        {
          "name": "shye.",
          "url": "https://open.spotify.com/artist/5SBFpt9Gz53LckT9guA7AS"
        }
      ],
      "duration_ms": 176000,
      "name": "Boy Meets World",
      "url": "https://open.spotify.com/track/2rwA0EpB6hN8WGlmwPSf8A"
    },
    {
      "added_at": "2022-03-23 13:28:07",
      "album": {
        "name": "Selfish",
        "url": "https://open.spotify.com/album/67pLH9BcT0kwLCfFErRuvO"
      },
      "artists": [
        {
          "name": "Good Boy Daisy",
          "url": "https://open.spotify.com/artist/48LeC49ZUI6oXfZrTA2QlL"
        }
      ],
      "duration_ms": 150657,
      "name": "Selfish",
      "url": "https://open.spotify.com/track/7eWHF1vaNW7W8W8GotYrlq"
    },
    {
      "added_at": "2022-03-23 13:28:07",
      "album": {
        "name": "All My Fault",
        "url": "https://open.spotify.com/album/5Mkk2sGhQatyKwo4hrdvKS"
      },
      "artists": [
        {
          "name": "Devon Again",
          "url": "https://open.spotify.com/artist/3xz28DkZR6bmPpVh6Rq13t"
        }
      ],
      "duration_ms": 182786,
      "name": "All My Fault",
      "url": "https://open.spotify.com/track/53lwPgJYa1cK61auYuVuMP"
    },
    {
      "added_at": "2022-03-23 13:28:07",
      "album": {
        "name": "An Honest Mess",
        "url": "https://open.spotify.com/album/4fhsPzxeog6vS0Koz8f47n"
      },
      "artists": [
        {
          "name": "MCK",
          "url": "https://open.spotify.com/artist/4gTs9iz3O0hzMwY2U2XKS7"
        },
        {
          "name": "Mountain Boy",
          "url": "https://open.spotify.com/artist/3qEnPaVdXvWJz4JZfRdqw7"
        }
      ],
      "duration_ms": 202397,
      "name": "An Honest Mess",
      "url": "https://open.spotify.com/track/00nJAeUvd37o65vdmqtg1G"
    },
    {
      "added_at": "2022-03-23 13:28:07",
      "album": {
        "name": "Another Life",
        "url": "https://open.spotify.com/album/0587bzXHHMFzUhk6ETNihl"
      },
      "artists": [
        {
          "name": "KOATES",
          "url": "https://open.spotify.com/artist/5YSPtpr66K8oOTvy3UjDcj"
        }
      ],
      "duration_ms": 162599,
      "name": "Another Life",
      "url": "https://open.spotify.com/track/0LnfUeqEA3NzFwbuIsUrlA"
    },
    {
      "added_at": "2022-03-23 13:28:07",
      "album": {
        "name": "Strangers",
        "url": "https://open.spotify.com/album/0USiFav7oOkHJXQFApIX47"
      },
      "artists": [
        {
          "name": "Izabel",
          "url": "https://open.spotify.com/artist/3YTr9y6XOl88xxHv246Vlf"
        }
      ],
      "duration_ms": 213060,
      "name": "Strangers",
      "url": "https://open.spotify.com/track/1lyZzZ1EP9vscUbBXNQYrx"
    },
    {
      "added_at": "2022-03-23 13:28:07",
      "album": {
        "name": "Good Time",
        "url": "https://open.spotify.com/album/2MMXRYeLPtmnPNPAYc8C4o"
      },
      "artists": [
        {
          "name": "Tsatsamis",
          "url": "https://open.spotify.com/artist/3z2RaxEObO8hXkvmG5xou0"
        }
      ],
      "duration_ms": 190009,
      "name": "Good Time",
      "url": "https://open.spotify.com/track/6DrIPRR1T24XUqmsW64cUF"
    },
    {
      "added_at": "2022-03-23 13:28:07",
      "album": {
        "name": "Icon",
        "url": "https://open.spotify.com/album/3H0LSJXc4oJl1XrHJjN0gn"
      },
      "artists": [
        {
          "name": "Shuba",
          "url": "https://open.spotify.com/artist/3Uios5Yyv4i8EBs9H3DUY5"
        }
      ],
      "duration_ms": 212192,
      "name": "Icon",
      "url": "https://open.spotify.com/track/0PZCXMrYcGYXhX3wCrkaL1"
    },
    {
      "added_at": "2022-03-23 13:28:07",
      "album": {
        "name": "Rush",
        "url": "https://open.spotify.com/album/1Td33W13Kvh7xAam42b2pK"
      },
      "artists": [
        {
          "name": "Seb Torgus",
          "url": "https://open.spotify.com/artist/39fzQ0Vv8BJ3J8bkf1VFUz"
        }
      ],
      "duration_ms": 218524,
      "name": "Rush",
      "url": "https://open.spotify.com/track/6DwesuBTzYmdAjTynjuKEd"
    },
    {
      "added_at": "2022-03-23 13:28:07",
      "album": {
        "name": "Red Flag",
        "url": "https://open.spotify.com/album/67hdpDqwwgqleopnJNGYnP"
      },
      "artists": [
        {
          "name": "Antigoni",
          "url": "https://open.spotify.com/artist/1w3S0hfHSbOupc4EVLRGrW"
        }
      ],
      "duration_ms": 116190,
      "name": "Red Flag",
      "url": "https://open.spotify.com/track/7G0qesP4auoQ1RhZXWE3Zs"
    },
    {
      "added_at": "2022-03-16 04:00:00",
      "album": {
        "name": "Good Again",
        "url": "https://open.spotify.com/album/2Hdksrwt6VaheLdI2sdzTb"
      },
      "artists": [
        {
          "name": "Sofia Quinn",
          "url": "https://open.spotify.com/artist/7aa9NIJCeJoYtpUL56UH6Q"
        }
      ],
      "duration_ms": 194528,
      "name": "Good Again",
      "url": "https://open.spotify.com/track/2aoqTTOrZaLH5JBac28npQ"
    },
    {
      "added_at": "2022-03-23 13:28:07",
      "album": {
        "name": "Mistakes Were Made",
        "url": "https://open.spotify.com/album/3wreBZPIdf6y5h56X46LJn"
      },
      "artists": [
        {
          "name": "John Michael Howell",
          "url": "https://open.spotify.com/artist/4BqK6JLgMwQ99hx85DxNhP"
        }
      ],
      "duration_ms": 213893,
      "name": "Mistakes Were Made",
      "url": "https://open.spotify.com/track/2xHHLxTDWQpiIzzYL8rzdx"
    },
    {
      "added_at": "2022-03-16 04:00:00",
      "album": {
        "name": "that was quick!",
        "url": "https://open.spotify.com/album/5pUdobn8VDjZku5tmsiCXa"
      },
      "artists": [
        {
          "name": "Alfie Jukes",
          "url": "https://open.spotify.com/artist/06qfcPQQZ3AplWOg3KxsQ9"
        }
      ],
      "duration_ms": 166391,
      "name": "that was quick!",
      "url": "https://open.spotify.com/track/36tVh8MZ2bxliGj0eJyKsX"
    },
    {
      "added_at": "2022-03-23 13:28:07",
      "album": {
        "name": "That's the thing x",
        "url": "https://open.spotify.com/album/6m3nu19SylZYD3mVoL8ofF"
      },
      "artists": [
        {
          "name": "PRINS",
          "url": "https://open.spotify.com/artist/1aA95KMV62fwsApbrObQwq"
        }
      ],
      "duration_ms": 231019,
      "name": "That's the thing x",
      "url": "https://open.spotify.com/track/6obaKy6dy2P9cNQPEKzA16"
    },
    {
      "added_at": "2022-03-23 13:28:07",
      "album": {
        "name": "van gogh",
        "url": "https://open.spotify.com/album/5VI3LQqNNX2ptjVQgmff3a"
      },
      "artists": [
        {
          "name": "Avril Jensen",
          "url": "https://open.spotify.com/artist/5V9RpFO4rgqQ1P5ZLbMVqA"
        }
      ],
      "duration_ms": 206114,
      "name": "van gogh",
      "url": "https://open.spotify.com/track/5rfuxu9SeVji8qyeeltjI6"
    },
    {
      "added_at": "2022-03-23 13:28:07",
      "album": {
        "name": "cool water",
        "url": "https://open.spotify.com/album/1kCw98SsS5gJ2C1gJwF5JL"
      },
      "artists": [
        {
          "name": "dayaway",
          "url": "https://open.spotify.com/artist/6doiARNekKDdYtgBXIE5tX"
        }
      ],
      "duration_ms": 198750,
      "name": "cool water",
      "url": "https://open.spotify.com/track/188d9yxQ59ZUuHnJ927vXM"
    },
    {
      "added_at": "2022-03-23 13:28:07",
      "album": {
        "name": "Animals",
        "url": "https://open.spotify.com/album/0P6sKlV8Vt9WmKYEheKfHt"
      },
      "artists": [
        {
          "name": "Dakota North",
          "url": "https://open.spotify.com/artist/3jSpqzexmaN7fAcJ0R7pNx"
        }
      ],
      "duration_ms": 166746,
      "name": "Animals",
      "url": "https://open.spotify.com/track/71NICVYcw7O7dGTZCxTuPr"
    },
    {
      "added_at": "2022-03-23 13:28:07",
      "album": {
        "name": "DELETE MY HISTORY (ctrl+alt+delete)",
        "url": "https://open.spotify.com/album/2JIQgCa5NfPv4b2FXtWkIw"
      },
      "artists": [
        {
          "name": "Lola Scott",
          "url": "https://open.spotify.com/artist/6oU5PNSVWwkSZSXwsOVF3m"
        }
      ],
      "duration_ms": 190133,
      "name": "DELETE MY HISTORY (ctrl+alt+delete)",
      "url": "https://open.spotify.com/track/1wV8KInvXt4g7TVRnXZVNn"
    },
    {
      "added_at": "2022-03-23 13:28:07",
      "album": {
        "name": "Not a Vibe",
        "url": "https://open.spotify.com/album/4aY3IeMsbi1J2Q349VRHBE"
      },
      "artists": [
        {
          "name": "it's just Cat",
          "url": "https://open.spotify.com/artist/7vq7I1JhmEPWA6Lr9pU6d9"
        }
      ],
      "duration_ms": 157818,
      "name": "Not a Vibe",
      "url": "https://open.spotify.com/track/5shCS2mZchvAFWYBKNgi4D"
    },
    {
      "added_at": "2022-03-23 13:28:07",
      "album": {
        "name": "Unstoppable",
        "url": "https://open.spotify.com/album/5vaU6TcDVUW2kwBc5X1x6k"
      },
      "artists": [
        {
          "name": "Florent Brack",
          "url": "https://open.spotify.com/artist/78PHudnzyatBjlCF0zQm2W"
        }
      ],
      "duration_ms": 187270,
      "name": "Unstoppable",
      "url": "https://open.spotify.com/track/2M6J8pHKRNqzkSuULRC7bJ"
    },
    {
      "added_at": "2022-03-23 13:28:07",
      "album": {
        "name": "Back to You",
        "url": "https://open.spotify.com/album/58jIg843UC5iN5sGLoJWIp"
      },
      "artists": [
        {
          "name": "Adriana",
          "url": "https://open.spotify.com/artist/2h7JR7HbfDuNKibkk9GkDq"
        }
      ],
      "duration_ms": 156960,
      "name": "Back to You",
      "url": "https://open.spotify.com/track/7zjif2RAeR0LuzlW7OqPoo"
    },
    {
      "added_at": "2022-03-23 13:28:07",
      "album": {
        "name": "Flowers Don't Bloom",
        "url": "https://open.spotify.com/album/11pyqTNmHK8tND6zm2U8MC"
      },
      "artists": [
        {
          "name": "Josh Sahunta",
          "url": "https://open.spotify.com/artist/37aXAbBndtjTPR4aUKumLV"
        }
      ],
      "duration_ms": 190983,
      "name": "Flowers Don't Bloom",
      "url": "https://open.spotify.com/track/4Z0r6fXGGcEt1JODY6Og1F"
    },
    {
      "added_at": "2022-03-23 13:28:07",
      "album": {
        "name": "The Way You Love",
        "url": "https://open.spotify.com/album/4BIttrCCQhxvp6tufhYJza"
      },
      "artists": [
        {
          "name": "TITUS BANK",
          "url": "https://open.spotify.com/artist/6lO31QP9bo8C3ay6IxkIol"
        }
      ],
      "duration_ms": 200529,
      "name": "The Way You Love",
      "url": "https://open.spotify.com/track/34fKjKw3hyh13HQesfzHSe"
    },
    {
      "added_at": "2022-03-23 13:28:07",
      "album": {
        "name": "When You Love Someone",
        "url": "https://open.spotify.com/album/3Zg8pJZCrNDeR7NMkZCaCq"
      },
      "artists": [
        {
          "name": "Alessia De Gasperis",
          "url": "https://open.spotify.com/artist/27d6mRgPBvGasBzQ9KFMGO"
        }
      ],
      "duration_ms": 161358,
      "name": "When You Love Someone",
      "url": "https://open.spotify.com/track/0A5WWYXLTLpQ1IFBdgazI7"
    },
    {
      "added_at": "2022-03-23 13:28:07",
      "album": {
        "name": "Blurry",
        "url": "https://open.spotify.com/album/2JDIK3CYHce6Y7DYd7lE3U"
      },
      "artists": [
        {
          "name": "Eleven Point Two",
          "url": "https://open.spotify.com/artist/1Eq5pdKZxRMsjg7Z2nGwvO"
        }
      ],
      "duration_ms": 200084,
      "name": "Blurry",
      "url": "https://open.spotify.com/track/1iJ5MSw9fFnVqk3XpEe8Hz"
    },
    {
      "added_at": "2022-03-23 13:28:07",
      "album": {
        "name": "Planet",
        "url": "https://open.spotify.com/album/7xp7nyGsoccGncUZoITCZK"
      },
      "artists": [
        {
          "name": "Franko Gonzo",
          "url": "https://open.spotify.com/artist/07HyKUaifP40mpsVsLCacY"
        }
      ],
      "duration_ms": 197475,
      "name": "Planet",
      "url": "https://open.spotify.com/track/3n2gA5TniaGUbonCfnUpYf"
    },
    {
      "added_at": "2022-03-23 13:28:07",
      "album": {
        "name": "Rainbow",
        "url": "https://open.spotify.com/album/0yJzuT4T9Rf5H4sV1OFGsk"
      },
      "artists": [
        {
          "name": "Grace Pelle",
          "url": "https://open.spotify.com/artist/0sBS1xdoktPWXbo6iNOx8p"
        }
      ],
      "duration_ms": 204722,
      "name": "Rainbow",
      "url": "https://open.spotify.com/track/12Ir8MQzqu6X78vMwsublK"
    },
    {
      "added_at": "2022-03-23 13:28:07",
      "album": {
        "name": "Foundation",
        "url": "https://open.spotify.com/album/3uGD0fnPmRIJ4TY1Zjgg1a"
      },
      "artists": [
        {
          "name": "Nick Vyner",
          "url": "https://open.spotify.com/artist/2gmFaEvoRIXAetLvWOVeI7"
        }
      ],
      "duration_ms": 122933,
      "name": "Foundation",
      "url": "https://open.spotify.com/track/2NDbThn27kU4e61LUJmeYC"
    },
    {
      "added_at": "2022-03-23 13:28:07",
      "album": {
        "name": "fallin for you",
        "url": "https://open.spotify.com/album/1fYIWQ2t7tKAf13NL5BIgO"
      },
      "artists": [
        {
          "name": "Brooke Sause",
          "url": "https://open.spotify.com/artist/2hnqTA6CYC7oO1A3Yrxold"
        }
      ],
      "duration_ms": 219592,
      "name": "fallin for you",
      "url": "https://open.spotify.com/track/2mFNtlviWQWpmQx4ofKXxW"
    },
    {
      "added_at": "2022-03-16 04:00:00",
      "album": {
        "name": "Younger",
        "url": "https://open.spotify.com/album/592eABOwz4EtzLKV0KgUKF"
      },
      "artists": [
        {
          "name": "Kayla Thompson",
          "url": "https://open.spotify.com/artist/0Sflq5MAqI4tTFfqIOpar3"
        }
      ],
      "duration_ms": 212571,
      "name": "Younger",
      "url": "https://open.spotify.com/track/3YF3WkYkHyiEk8sqhyE2VQ"
    },
    {
      "added_at": "2022-03-16 04:00:00",
      "album": {
        "name": "Crime of the Century",
        "url": "https://open.spotify.com/album/3KFAfbgxPVWzvvENkeFxOv"
      },
      "artists": [
        {
          "name": "Emilee Moore",
          "url": "https://open.spotify.com/artist/21k39bIiVAame9O5MWRS4m"
        }
      ],
      "duration_ms": 169941,
      "name": "Crime of the Century",
      "url": "https://open.spotify.com/track/6VLrRwqYS9tHYRdWdBlMAL"
    },
    {
      "added_at": "2022-03-16 04:00:00",
      "album": {
        "name": "not this time",
        "url": "https://open.spotify.com/album/7j3N8YpNnd3wheFpNoJVmy"
      },
      "artists": [
        {
          "name": "Ben Ellis",
          "url": "https://open.spotify.com/artist/3u0GaOtYxsIbwldWs8dgE8"
        }
      ],
      "duration_ms": 158009,
      "name": "not this time",
      "url": "https://open.spotify.com/track/5zaDIJxDKZouDM7jP6hwIb"
    },
    {
      "added_at": "2022-03-16 04:00:00",
      "album": {
        "name": "baby steps",
        "url": "https://open.spotify.com/album/5WenMaK6Q4uDFngPC4KyP9"
      },
      "artists": [
        {
          "name": "COTTA",
          "url": "https://open.spotify.com/artist/56tLi5G28sgM5rmaDXaFyE"
        }
      ],
      "duration_ms": 236000,
      "name": "Trying",
      "url": "https://open.spotify.com/track/6IGjSOL2FNgVKgKAnl8oa6"
    },
    {
      "added_at": "2022-03-16 04:00:00",
      "album": {
        "name": "Sixteen",
        "url": "https://open.spotify.com/album/2OQTIknCPX400GUeWiwXrG"
      },
      "artists": [
        {
          "name": "Tess Clare",
          "url": "https://open.spotify.com/artist/0w3V7iEOBeQUDg8xm6NB6L"
        }
      ],
      "duration_ms": 218510,
      "name": "Sixteen",
      "url": "https://open.spotify.com/track/6wCowLIXN3MVgJcUwvr9Ph"
    },
    {
      "added_at": "2022-03-16 04:00:00",
      "album": {
        "name": "volkswagens",
        "url": "https://open.spotify.com/album/5lleMb5RdpoSGN8uGaOzYq"
      },
      "artists": [
        {
          "name": "dora.",
          "url": "https://open.spotify.com/artist/0Ym566deMKtIcLclCs6AqB"
        }
      ],
      "duration_ms": 160568,
      "name": "volkswagens",
      "url": "https://open.spotify.com/track/5lJKyrg4IRUEGN0eQao1JK"
    },
    {
      "added_at": "2022-03-16 04:00:00",
      "album": {
        "name": "Easier Said",
        "url": "https://open.spotify.com/album/4hKZOqBRw4EhTIQRvbwCd8"
      },
      "artists": [
        {
          "name": "Aint Afraid",
          "url": "https://open.spotify.com/artist/1E6I6xhlNmVIgnDGkikmj5"
        }
      ],
      "duration_ms": 220408,
      "name": "Easier Said",
      "url": "https://open.spotify.com/track/4xtovOO8zN3TYmC8kcLcN1"
    },
    {
      "added_at": "2022-03-16 04:00:00",
      "album": {
        "name": "Lost With You",
        "url": "https://open.spotify.com/album/7s83UPvo27RHReBXUW8oGH"
      },
      "artists": [
        {
          "name": "Raye Zaragoza",
          "url": "https://open.spotify.com/artist/14w8BJMukAOb1KQuY3d5Jc"
        },
        {
          "name": "Viv Parker",
          "url": "https://open.spotify.com/artist/1e9EAdBnrbddrBATSzZfmW"
        }
      ],
      "duration_ms": 201000,
      "name": "Lost With You",
      "url": "https://open.spotify.com/track/6TqpVC4vqsZsFT0AH5doGJ"
    },
    {
      "added_at": "2022-03-16 04:00:00",
      "album": {
        "name": "NOVOCAINE",
        "url": "https://open.spotify.com/album/4PCqUVy5R8moBntbO6IygJ"
      },
      "artists": [
        {
          "name": "Saya",
          "url": "https://open.spotify.com/artist/5M60ox9b9C4RSPOYYQLTae"
        }
      ],
      "duration_ms": 190789,
      "name": "NOVOCAINE",
      "url": "https://open.spotify.com/track/5bwAuezZuH8if87TRA3yXV"
    },
    {
      "added_at": "2022-03-16 04:00:00",
      "album": {
        "name": "Kiss Me Right Now",
        "url": "https://open.spotify.com/album/6KOGImqjlM8wNaL1JHtJXy"
      },
      "artists": [
        {
          "name": "TATYANA",
          "url": "https://open.spotify.com/artist/40SwTLJmxQgWXTFi4YUKyP"
        }
      ],
      "duration_ms": 240000,
      "name": "Kiss Me Right Now",
      "url": "https://open.spotify.com/track/2Wxj1gIUP2B6Eb0uWeqa1R"
    },
    {
      "added_at": "2022-03-02 05:00:00",
      "album": {
        "name": "Sensitive Subject",
        "url": "https://open.spotify.com/album/3yIVjEUIZMCieIcJywAkfT"
      },
      "artists": [
        {
          "name": "Grey Zeigler",
          "url": "https://open.spotify.com/artist/7KPQ1gyjGeNrDCySwrXAhI"
        }
      ],
      "duration_ms": 142576,
      "name": "Sensitive Subject",
      "url": "https://open.spotify.com/track/2ZtEW8JaHmUmu85Rqd5lWi"
    },
    {
      "added_at": "2022-03-16 04:00:00",
      "album": {
        "name": "Daydream",
        "url": "https://open.spotify.com/album/01r1tuIZyPp6nmLG2Q4Vnu"
      },
      "artists": [
        {
          "name": "Lily Meola",
          "url": "https://open.spotify.com/artist/5WC6EbIrTO76x30w5LtzS6"
        }
      ],
      "duration_ms": 187752,
      "name": "Flaws",
      "url": "https://open.spotify.com/track/5qiECQN5ZamBAteYwFKAZc"
    },
    {
      "added_at": "2022-03-16 04:00:00",
      "album": {
        "name": "super 8",
        "url": "https://open.spotify.com/album/7DPrCyq7eeLL7WJD64QyaJ"
      },
      "artists": [
        {
          "name": "Jack Price",
          "url": "https://open.spotify.com/artist/3LX53Q6Lfgpr309q3yiHMh"
        }
      ],
      "duration_ms": 167917,
      "name": "super 8",
      "url": "https://open.spotify.com/track/4Exb0V85Rarw8Fk196x2sS"
    },
    {
      "added_at": "2022-03-16 04:00:00",
      "album": {
        "name": "Who's Gonna Hold You Tonight",
        "url": "https://open.spotify.com/album/0Ugwf7D4x4zpNwqPYhwcez"
      },
      "artists": [
        {
          "name": "The Yves",
          "url": "https://open.spotify.com/artist/50CeFDCHW8eEwymrHFAeKL"
        }
      ],
      "duration_ms": 197647,
      "name": "Who's Gonna Hold You Tonight",
      "url": "https://open.spotify.com/track/4anoTM56qvfkXVdUiUmmSr"
    },
    {
      "added_at": "2022-03-16 04:00:00",
      "album": {
        "name": "Happens All The Time",
        "url": "https://open.spotify.com/album/4I5XTcRXTDNmE6NT0oMn2X"
      },
      "artists": [
        {
          "name": "Tash",
          "url": "https://open.spotify.com/artist/3kX6nt9QiDarAkCsIGRIgR"
        }
      ],
      "duration_ms": 163545,
      "name": "Happens All The Time",
      "url": "https://open.spotify.com/track/1HezVdieJrvo38VkRJGw3n"
    },
    {
      "added_at": "2022-03-16 04:00:00",
      "album": {
        "name": "909s and Hard Times",
        "url": "https://open.spotify.com/album/4v6GPaHX2z13aB8AtDpNSQ"
      },
      "artists": [
        {
          "name": "Me Nd Adam",
          "url": "https://open.spotify.com/artist/58a532kDwpexiy0e42wZph"
        }
      ],
      "duration_ms": 158557,
      "name": "909s and Hard Times",
      "url": "https://open.spotify.com/track/75X9GHl64alVkDRX6gVYbP"
    },
    {
      "added_at": "2022-03-09 05:00:00",
      "album": {
        "name": "crying on my birthday",
        "url": "https://open.spotify.com/album/4PGr5dJwJNa6lUcpP9fiY6"
      },
      "artists": [
        {
          "name": "COLE",
          "url": "https://open.spotify.com/artist/3QYpKiqpeL1EKF2NF4kOMA"
        }
      ],
      "duration_ms": 223032,
      "name": "crying on my birthday",
      "url": "https://open.spotify.com/track/4DMr7EhBi7GsjJZahnuFRI"
    },
    {
      "added_at": "2022-03-16 04:00:00",
      "album": {
        "name": "Waves",
        "url": "https://open.spotify.com/album/3GihWBWJFiGg8mDbgapuPg"
      },
      "artists": [
        {
          "name": "Mark Ambor",
          "url": "https://open.spotify.com/artist/11p2E654TTU8e0nZWBR4AL"
        }
      ],
      "duration_ms": 166280,
      "name": "Waves",
      "url": "https://open.spotify.com/track/4YMSk1mVIn9R6OBhXy8EXg"
    },
    {
      "added_at": "2022-03-16 04:00:00",
      "album": {
        "name": "Alternative Current",
        "url": "https://open.spotify.com/album/6e16HQDDp22vv90xuKRmMF"
      },
      "artists": [
        {
          "name": "Harrison Sands",
          "url": "https://open.spotify.com/artist/5lwE4ASworJdeRDXu5g9en"
        }
      ],
      "duration_ms": 186000,
      "name": "Alternative Current",
      "url": "https://open.spotify.com/track/7Mg1jM8U9ss14MVPmYugXg"
    },
    {
      "added_at": "2022-03-16 04:00:00",
      "album": {
        "name": "My Adeline",
        "url": "https://open.spotify.com/album/3xyqEqodJFI4DaSNc8dUsm"
      },
      "artists": [
        {
          "name": "Isla Rose",
          "url": "https://open.spotify.com/artist/7id0KhxSicAZjV9e0aDTie"
        }
      ],
      "duration_ms": 181778,
      "name": "My Adeline",
      "url": "https://open.spotify.com/track/3T72wXLxck8AboLdSvEW3Y"
    },
    {
      "added_at": "2022-03-16 04:00:00",
      "album": {
        "name": "Buzzcut",
        "url": "https://open.spotify.com/album/4Ku9F96AbFCtQBVYzVvB9z"
      },
      "artists": [
        {
          "name": "Estella Dawn",
          "url": "https://open.spotify.com/artist/00SIMc8XBD6NezPkMpkMcL"
        }
      ],
      "duration_ms": 196880,
      "name": "Buzzcut",
      "url": "https://open.spotify.com/track/7IWPJElIZaHh7eyvg6D46d"
    },
    {
      "added_at": "2022-03-16 04:00:00",
      "album": {
        "name": "Blank Page",
        "url": "https://open.spotify.com/album/7hKEp9Sh7BwASAeHolaONj"
      },
      "artists": [
        {
          "name": "MISSY",
          "url": "https://open.spotify.com/artist/3Fwrv2f2K0AxSDCrS8qZhD"
        }
      ],
      "duration_ms": 149727,
      "name": "Blank Page",
      "url": "https://open.spotify.com/track/0CWWCOjNGeo40Kl0XbkYe4"
    },
    {
      "added_at": "2022-03-16 04:00:00",
      "album": {
        "name": "Crash",
        "url": "https://open.spotify.com/album/0pZ8nqEGFIHcCC1i9sE2lM"
      },
      "artists": [
        {
          "name": "Badley",
          "url": "https://open.spotify.com/artist/2mnmAUiXWb5Xck3XvpU99C"
        }
      ],
      "duration_ms": 199200,
      "name": "Crash",
      "url": "https://open.spotify.com/track/0djs95BuqmrmhYiPiMyBLP"
    },
    {
      "added_at": "2022-03-16 04:00:00",
      "album": {
        "name": "too much too soon",
        "url": "https://open.spotify.com/album/2CHJagCyB48dhJhgh594ZK"
      },
      "artists": [
        {
          "name": "Cind\u00eb",
          "url": "https://open.spotify.com/artist/6UmkItoyk0QIRoEQGMhEYz"
        }
      ],
      "duration_ms": 223106,
      "name": "too much too soon",
      "url": "https://open.spotify.com/track/2JJoUZhEMlUHEWYLMA58yY"
    },
    {
      "added_at": "2022-03-16 04:00:00",
      "album": {
        "name": "Becky's Plan",
        "url": "https://open.spotify.com/album/0xqb3ud21ynwqavfw3vPSf"
      },
      "artists": [
        {
          "name": "CODY JON",
          "url": "https://open.spotify.com/artist/5xYvg2nZQcavaPwYOcOYRD"
        }
      ],
      "duration_ms": 185485,
      "name": "Becky's Plan",
      "url": "https://open.spotify.com/track/427JUJckVwkdx0susZPzjh"
    },
    {
      "added_at": "2022-03-16 04:00:00",
      "album": {
        "name": "Gone",
        "url": "https://open.spotify.com/album/5yTWLRohkcog27577nF1zd"
      },
      "artists": [
        {
          "name": "NOA",
          "url": "https://open.spotify.com/artist/5OaWY1HjWremIVRztYS1xG"
        }
      ],
      "duration_ms": 155120,
      "name": "Gone",
      "url": "https://open.spotify.com/track/3cqTsnVsjJxf3WFmk2JWOr"
    },
    {
      "added_at": "2022-03-16 04:00:00",
      "album": {
        "name": "Mood Swings",
        "url": "https://open.spotify.com/album/4Xqs6V2KZfeXJzU2UksxlB"
      },
      "artists": [
        {
          "name": "Ava Maybee",
          "url": "https://open.spotify.com/artist/56XHwBrYEOBDDGKr7BLDv9"
        }
      ],
      "duration_ms": 176692,
      "name": "Mood Swings",
      "url": "https://open.spotify.com/track/24ZKPETbnV9z8G0BlIS8Mt"
    },
    {
      "added_at": "2022-03-16 04:00:00",
      "album": {
        "name": "YOYO'S HOUSE",
        "url": "https://open.spotify.com/album/5y0bofBZUnH3hZYsYErwD1"
      },
      "artists": [
        {
          "name": "Yoandri",
          "url": "https://open.spotify.com/artist/7uCNYKOeuyGcoxaP1Y095d"
        }
      ],
      "duration_ms": 234720,
      "name": "YOYO'S HOUSE",
      "url": "https://open.spotify.com/track/5YIzo69TOuvkl2IsIvEL63"
    },
    {
      "added_at": "2022-03-09 05:00:00",
      "album": {
        "name": "All The Cool Kids Get High",
        "url": "https://open.spotify.com/album/3LHdv4Z4Q9ECBQE5JqVbh1"
      },
      "artists": [
        {
          "name": "Leah Sykes",
          "url": "https://open.spotify.com/artist/3OYYN1sVAjeYS6sRlCH19H"
        }
      ],
      "duration_ms": 177809,
      "name": "All The Cool Kids Get High",
      "url": "https://open.spotify.com/track/5fmEmgItv5hpXd5yGbpLxT"
    },
    {
      "added_at": "2022-03-09 05:00:00",
      "album": {
        "name": "READ",
        "url": "https://open.spotify.com/album/7uMlhSlAXQWMfrgcnJ7Xxi"
      },
      "artists": [
        {
          "name": "Zoe A'dore",
          "url": "https://open.spotify.com/artist/3LGngRo9kg4ETVaiRQ0ZgY"
        }
      ],
      "duration_ms": 168956,
      "name": "READ",
      "url": "https://open.spotify.com/track/1o2SurUyAJFFkf0kjSMKo1"
    },
    {
      "added_at": "2022-03-02 05:00:00",
      "album": {
        "name": "HAUNTED",
        "url": "https://open.spotify.com/album/0NJhMR5JGpXyDaqCgKywvf"
      },
      "artists": [
        {
          "name": "Isabel LaRosa",
          "url": "https://open.spotify.com/artist/5arKwJZEvT5uKq4o0JfqR4"
        }
      ],
      "duration_ms": 136363,
      "name": "HAUNTED",
      "url": "https://open.spotify.com/track/2y3kTv2pxaLM7YEwyazSH7"
    },
    {
      "added_at": "2022-03-09 05:00:00",
      "album": {
        "name": "dougie jones",
        "url": "https://open.spotify.com/album/7txL4P1ciH1FRiyzjWJSy9"
      },
      "artists": [
        {
          "name": "Lubalin",
          "url": "https://open.spotify.com/artist/6lt3CXKfhLXjYl2VFD6vN4"
        }
      ],
      "duration_ms": 216426,
      "name": "dougie jones",
      "url": "https://open.spotify.com/track/1cxf0uqgT8mrRUryRj2GCx"
    },
    {
      "added_at": "2022-03-09 05:00:00",
      "album": {
        "name": "Nightfall Feelings",
        "url": "https://open.spotify.com/album/0DxJpBkuIlXcrOTKQ6oHz8"
      },
      "artists": [
        {
          "name": "Pure Shores",
          "url": "https://open.spotify.com/artist/42CdKQR7lo8cgIyufa0DQr"
        }
      ],
      "duration_ms": 213564,
      "name": "Wasting My Time",
      "url": "https://open.spotify.com/track/0NO8wmpvCOYdGs6bKtS26P"
    },
    {
      "added_at": "2022-03-09 05:00:00",
      "album": {
        "name": "Care",
        "url": "https://open.spotify.com/album/5jgVpT4qJ2buE9VAxVrT5G"
      },
      "artists": [
        {
          "name": "\u00d3d\u00fa",
          "url": "https://open.spotify.com/artist/5J0S0VMJPab8FUbu3vJ2ds"
        }
      ],
      "duration_ms": 186005,
      "name": "Care",
      "url": "https://open.spotify.com/track/01WVhnWgcISq2mIimBywbV"
    },
    {
      "added_at": "2022-03-09 05:00:00",
      "album": {
        "name": "Money",
        "url": "https://open.spotify.com/album/4vCFA40in0IrEpRRonvweD"
      },
      "artists": [
        {
          "name": "Ayla D'lyla",
          "url": "https://open.spotify.com/artist/1gtS3u4J43CYspyLmJAJu5"
        }
      ],
      "duration_ms": 221000,
      "name": "Money",
      "url": "https://open.spotify.com/track/6FjfHnDM6YGSLMBmCX1yXl"
    },
    {
      "added_at": "2022-03-09 05:00:00",
      "album": {
        "name": "NEVER CRY AGAIN",
        "url": "https://open.spotify.com/album/1uYX907pgQI6YblNc087rK"
      },
      "artists": [
        {
          "name": "John Michael Howell",
          "url": "https://open.spotify.com/artist/4BqK6JLgMwQ99hx85DxNhP"
        }
      ],
      "duration_ms": 164573,
      "name": "NEVER CRY AGAIN",
      "url": "https://open.spotify.com/track/4oHUV9PR1jCJNqZ35xuSZ1"
    },
    {
      "added_at": "2022-03-09 05:00:00",
      "album": {
        "name": "bittersweet",
        "url": "https://open.spotify.com/album/5Zx921CEjBDLKPsBFPFBoF"
      },
      "artists": [
        {
          "name": "LORA",
          "url": "https://open.spotify.com/artist/3sJr6yhJiNvyTbgrNRDkr8"
        }
      ],
      "duration_ms": 163504,
      "name": "bittersweet",
      "url": "https://open.spotify.com/track/4f0HrumuDOiNdzXRGKq5yB"
    },
    {
      "added_at": "2022-03-09 05:00:00",
      "album": {
        "name": "She (Nothing Like Me)",
        "url": "https://open.spotify.com/album/6G9FN3eiln5U6lesqOyakp"
      },
      "artists": [
        {
          "name": "Jess Spink",
          "url": "https://open.spotify.com/artist/1tgraTEgO9OYhLUUdpn7Jz"
        }
      ],
      "duration_ms": 145440,
      "name": "She (Nothing Like Me)",
      "url": "https://open.spotify.com/track/50DgNkbLNGSBcEO44Pj1ah"
    },
    {
      "added_at": "2022-03-09 05:00:00",
      "album": {
        "name": "Mutual XO",
        "url": "https://open.spotify.com/album/4poZocs3xwN5Xp0WgdQU46"
      },
      "artists": [
        {
          "name": "Kota Banks",
          "url": "https://open.spotify.com/artist/6qjD8KqRe2dyNBsq1RcpaT"
        }
      ],
      "duration_ms": 172331,
      "name": "Mutual XO",
      "url": "https://open.spotify.com/track/5IGoUYZdWjfTUjGlfeTKRc"
    },
    {
      "added_at": "2022-03-09 05:00:00",
      "album": {
        "name": "marriage story",
        "url": "https://open.spotify.com/album/79jhHZ1Kdq8KQI3nLoiM0A"
      },
      "artists": [
        {
          "name": "Devon Gabriella",
          "url": "https://open.spotify.com/artist/1rfIKfqoygAsxTWBdzVO2i"
        }
      ],
      "duration_ms": 181417,
      "name": "marriage story",
      "url": "https://open.spotify.com/track/30IQqleF2IxItCSY7vaj8C"
    },
    {
      "added_at": "2022-03-09 05:00:00",
      "album": {
        "name": "im not important",
        "url": "https://open.spotify.com/album/2ZwUbHoAJeIer3MOACR5uJ"
      },
      "artists": [
        {
          "name": "Llunr",
          "url": "https://open.spotify.com/artist/1r2EC1UsQXwtqVN9valnT2"
        }
      ],
      "duration_ms": 125060,
      "name": "im not important",
      "url": "https://open.spotify.com/track/4idQrHSD0CPe5jHrPcEHNb"
    },
    {
      "added_at": "2022-02-23 05:00:00",
      "album": {
        "name": "FUCK MY EXES",
        "url": "https://open.spotify.com/album/0HkYxUI2kqixf8MgY8fUhi"
      },
      "artists": [
        {
          "name": "Jules Paymer",
          "url": "https://open.spotify.com/artist/5RsYo1rckHPH2ERWm3tGeS"
        }
      ],
      "duration_ms": 170015,
      "name": "FUCK MY EXES",
      "url": "https://open.spotify.com/track/03xqIbvagvjf3K75qqL0fC"
    },
    {
      "added_at": "2022-03-09 05:00:00",
      "album": {
        "name": "How to Be Alone",
        "url": "https://open.spotify.com/album/5cFmtcEpZiTgFTR26I1TwV"
      },
      "artists": [
        {
          "name": "Rachel Grae",
          "url": "https://open.spotify.com/artist/0ekCwZGQUkAISV1h48jlHn"
        }
      ],
      "duration_ms": 151077,
      "name": "How to Be Alone",
      "url": "https://open.spotify.com/track/6xWHPPreZAD93a1g14Noun"
    },
    {
      "added_at": "2022-02-09 05:08:15",
      "album": {
        "name": "Trophy",
        "url": "https://open.spotify.com/album/3DcH7VLRiXxiuWu91XjJy7"
      },
      "artists": [
        {
          "name": "TAELA",
          "url": "https://open.spotify.com/artist/0UpJN0IU36gOyMJLHYHTYq"
        }
      ],
      "duration_ms": 160173,
      "name": "Trophy",
      "url": "https://open.spotify.com/track/5igLTHeeq84I50vFL4ZS2j"
    },
    {
      "added_at": "2022-03-02 05:00:00",
      "album": {
        "name": "Seen",
        "url": "https://open.spotify.com/album/4pQgKTITrIp8lNGKwNWjWg"
      },
      "artists": [
        {
          "name": "DEZI",
          "url": "https://open.spotify.com/artist/3X9hlPTLBIZ9pEONCQnjTm"
        }
      ],
      "duration_ms": 207272,
      "name": "Seen",
      "url": "https://open.spotify.com/track/56ybiNUE5Gim5BtlWRD40o"
    },
    {
      "added_at": "2022-03-02 05:00:00",
      "album": {
        "name": "The Basics Are Coming Back / Burnout",
        "url": "https://open.spotify.com/album/23x0JjCIYxQkBcASjtskM1"
      },
      "artists": [
        {
          "name": "0171",
          "url": "https://open.spotify.com/artist/134QvSuQi0iORVoQQHqXqX"
        }
      ],
      "duration_ms": 218595,
      "name": "The Basics Are Coming Back",
      "url": "https://open.spotify.com/track/0LVjkXEJaDB4xRfsz6CUgB"
    },
    {
      "added_at": "2022-03-02 05:00:00",
      "album": {
        "name": "Madonna",
        "url": "https://open.spotify.com/album/2uNNQws3ix4ZyVxueGd2un"
      },
      "artists": [
        {
          "name": "Juliana Madrid",
          "url": "https://open.spotify.com/artist/6RhkgeqhRai3jy4ULSlxFx"
        }
      ],
      "duration_ms": 192133,
      "name": "Madonna",
      "url": "https://open.spotify.com/track/1eCdsyHZVqHSi5jhwc4TLs"
    },
    {
      "added_at": "2022-03-02 05:00:00",
      "album": {
        "name": "Oddities & Prodigies",
        "url": "https://open.spotify.com/album/46n8rL1vHBdtUh9x7Bcud1"
      },
      "artists": [
        {
          "name": "Caroline Romano",
          "url": "https://open.spotify.com/artist/1MgbE6bu4MzbVLfAesPRol"
        }
      ],
      "duration_ms": 119500,
      "name": "Oddities and Prodigies",
      "url": "https://open.spotify.com/track/4BG1QQGeyyssmRKy0OuXlm"
    },
    {
      "added_at": "2022-03-02 05:00:00",
      "album": {
        "name": "you make me feel",
        "url": "https://open.spotify.com/album/4GH2Qzq4oWm62V84FYYg38"
      },
      "artists": [
        {
          "name": "Delanie Leclerc",
          "url": "https://open.spotify.com/artist/547XK7rrl55NSCTqDa7TUx"
        }
      ],
      "duration_ms": 191307,
      "name": "you make me feel",
      "url": "https://open.spotify.com/track/3fSXG6hm7U9zHja6zgTsUG"
    },
    {
      "added_at": "2022-03-02 05:00:00",
      "album": {
        "name": "last paycheck",
        "url": "https://open.spotify.com/album/1tkHBQQu15RjTMKR29pua8"
      },
      "artists": [
        {
          "name": "Rachel Bochner",
          "url": "https://open.spotify.com/artist/6AdwNKE3DsPrlNNCIzdZXz"
        }
      ],
      "duration_ms": 169524,
      "name": "last paycheck",
      "url": "https://open.spotify.com/track/3j40QQw846gskVZbjvsHUc"
    }
  ],
  "unique_name": "Fresh Finds Pop",
  "url": "https://open.spotify.com/playlist/37i9dQZF1DX3u9TSHqpdJC"
}
